Metadata-Version: 1.1
Name: vdt.simpleaptrepo
Version: 0.0.4
Summary: A simple command line utility to create a debian repository
Home-page: https://github.com/devopsconsulting/vdt.simpleaptrepo
Author: Martijn Jacobs
Author-email: martijn@devopsconsulting.nl
License: BSD
Platform: UNKNOWN
Classifier: License :: OSI Approved :: BSD License
Classifier: Operating System :: Unix
Classifier: Programming Language :: Python
Classifier: Programming Language :: Python :: 2
Classifier: Programming Language :: Python :: 2.7
Classifier: Programming Language :: Python :: 3
Classifier: Programming Language :: Python :: 3.5
Classifier: Programming Language :: Python :: 3.6
